ollamagent/__init__.py
ollamagent/_prompt.py
ollamagent/agent.py
ollamagent/client.py
ollamagent/exceptions.py
ollamagent/proxy.py
ollamagent/py.typed
ollamagent/tool.py
ollamagent/utils.py
ollamagent-0.0.4.dist-info/METADATA
ollamagent-0.0.4.dist-info/WHEEL
ollamagent-0.0.4.dist-info/RECORD
