Metadata-Version: 2.1
Name: ollamagent
Version: 0.0.4
Summary: A thin wrapper around `ollama` library
Author: obahamonde
Author-email: o.bahamonde@globant.com
Requires-Python: >=3.9,<4.0
Classifier: Programming Language :: Python :: 3
Classifier: Programming Language :: Python :: 3.9
Classifier: Programming Language :: Python :: 3.10
Classifier: Programming Language :: Python :: 3.11
Classifier: Programming Language :: Python :: 3.12
Requires-Dist: jinja2 (>=3.1.3,<4.0.0)
Requires-Dist: ollama (>=0.1.4,<0.2.0)
Requires-Dist: pydantic (>=2.5.3,<3.0.0)
Requires-Dist: rich (>=13.7.0,<14.0.0)
Requires-Dist: tenacity (>=8.2.3,<9.0.0)
